LICENSE
MANIFEST.in
README.md
requirements.txt
setup.py
cloudinary_cli/__init__.py
cloudinary_cli/cli.py
cloudinary_cli/cli_group.py
cloudinary_cli/defaults.py
cloudinary_cli/version.py
cloudinary_cli.egg-info/PKG-INFO
cloudinary_cli.egg-info/SOURCES.txt
cloudinary_cli.egg-info/dependency_links.txt
cloudinary_cli.egg-info/entry_points.txt
cloudinary_cli.egg-info/not-zip-safe
cloudinary_cli.egg-info/requires.txt
cloudinary_cli.egg-info/top_level.txt
cloudinary_cli/core/__init__.py
cloudinary_cli/core/admin.py
cloudinary_cli/core/config.py
cloudinary_cli/core/overrides.py
cloudinary_cli/core/provisioning.py
cloudinary_cli/core/search.py
cloudinary_cli/core/uploader.py
cloudinary_cli/core/utils.py
cloudinary_cli/modules/__init__.py
cloudinary_cli/modules/clone.py
cloudinary_cli/modules/make.py
cloudinary_cli/modules/migrate.py
cloudinary_cli/modules/regen_derived.py
cloudinary_cli/modules/sync.py
cloudinary_cli/modules/upload_dir.py
cloudinary_cli/samples/__init__.py
cloudinary_cli/templates/html/media_library_widget
cloudinary_cli/templates/html/product_gallery
cloudinary_cli/templates/html/upload_widget
cloudinary_cli/templates/html/video_player
cloudinary_cli/templates/node/upload
cloudinary_cli/templates/python/base
cloudinary_cli/templates/python/explicit
cloudinary_cli/templates/python/find_all_empty_folders
cloudinary_cli/templates/python/upload
cloudinary_cli/templates/ruby/upload
cloudinary_cli/utils/__init__.py
cloudinary_cli/utils/api_utils.py
cloudinary_cli/utils/config_utils.py
cloudinary_cli/utils/file_utils.py
cloudinary_cli/utils/json_utils.py
cloudinary_cli/utils/search_utils.py
cloudinary_cli/utils/utils.py
test/__init__.py
test/helper_test.py
test/test_cli.py
test/test_cli_api.py
test/test_cli_config.py
test/test_cli_samples.py
test/test_cli_search_api.py
test/test_cli_url.py
test/test_cli_utils.py
test/test_file_utils.py
test/test_search_utils.py
test/test_utils.py
test/test_modules/__init__.py
test/test_modules/test_cli_clone.py
test/test_modules/test_cli_make.py
test/test_modules/test_cli_sync.py
test/test_modules/test_cli_upload_dir.py