Metadata-Version: 2.1
Name: cloudinary-cli
Version: 1.14.0
Summary: A command line interface for Cloudinary with full API support
Home-page: https://github.com/cloudinary/cloudinary-cli
Author: Cloudinary, Brian Luk
Author-email: info@cloudinary.com, lukitsbrian@gmail.com
License: MIT
Keywords: cloudinary cli pycloudinary image video digital asset management command line interface transformation friendly easy flexible
Classifier: Programming Language :: Python :: 3 :: Only
Classifier: License :: OSI Approved :: MIT License
Classifier: Operating System :: OS Independent
Requires-Python: >=3.6.0
License-File: LICENSE
Requires-Dist: cloudinary>=1.42.2
Requires-Dist: pygments
Requires-Dist: jinja2
Requires-Dist: click
Requires-Dist: click-log
Requires-Dist: requests
Requires-Dist: docstring-parser
Requires-Dist: urllib3>=2.2.2
Requires-Dist: zipp>=3.19.1
